{
    "name": "@paypal/sdk-release",
    "dist-tags": {
        "latest": "5.0.413",
        "active-test": "5.0.413",
        "active-local": "5.0.413",
        "active-stage": "5.0.413",
        "active-sandbox": "5.0.317",
        "active-production": "5.0.317"
    },
    "versions": {
        "5.0.317": {
            "dependencies": {
                "@braintree/browser-detection": "1.7.0",
                "@braintree/iframer": "1.0.3",
                "@braintree/sanitize-url": "2.1.0",
                "@braintree/wrap-promise": "1.1.1",
                "@krakenjs/beaver-logger": "5.0.1",
                "@krakenjs/belter": "2.1.2",
                "@krakenjs/cross-domain-safe-weakmap": "2.0.3",
                "@krakenjs/cross-domain-utils": "3.0.2",
                "@krakenjs/jsx-pragmatic": "3.0.0",
                "@krakenjs/post-robot": "11.0.0",
                "@krakenjs/universal-serialize": "2.0.0",
                "@krakenjs/zalgo-promise": "2.0.1",
                "@krakenjs/zoid": "10.1.0",
                "@paypal/card-components": "1.0.54",
                "@paypal/checkout-components": "5.0.226",
                "@paypal/common-components": "1.0.31",
                "@paypal/example-components": "1.0.28",
                "@paypal/funding-components": "1.0.28",
                "@paypal/identity-components": "5.0.11",
                "@paypal/messaging-components": "1.34.6",
                "@paypal/muse-components": "1.3.85",
                "@paypal/sdk-client": "4.0.167",
                "@paypal/sdk-constants": "1.0.122",
                "@paypal/sdk-logos": "1.0.46",
                "bowser": "2.11.0",
                "braintree-web": "3.33.0",
                "card-validator": "4.3.0",
                "core-js-pure": "3.22.8",
                "credit-card-type": "6.3.0",
                "framebus": "3.0.1",
                "hi-base32": "0.5.1",
                "inject-stylesheet": "1.0.0",
                "promise-polyfill": "7.0.2",
                "restricted-input": "1.2.7",
                "whatwg-fetch": "3.6.2"
            },
            "dist": {
                "tarball": "https://www.paypalobjects.com/js-sdk-release/5.0.413/paypal/sdk-release/tarballs/5.0.317.tgz"
            },
            "repository": {
                "url": "git://github.com/paypal/paypal-sdk-release.git"
            },
            "gitHead": "7d15f408ae89cde5c54dc6b7e96364907ab5faa6"
        },
        "5.0.413": {
            "dependencies": {
                "@braintree/asset-loader": "2.0.0",
                "@braintree/browser-detection": "1.7.0",
                "@braintree/iframer": "1.0.3",
                "@braintree/sanitize-url": "2.1.0",
                "@braintree/wrap-promise": "1.1.1",
                "@krakenjs/beaver-logger": "5.5.0",
                "@krakenjs/belter": "2.3.1",
                "@krakenjs/cross-domain-safe-weakmap": "2.0.3",
                "@krakenjs/cross-domain-utils": "3.1.0",
                "@krakenjs/jsx-pragmatic": "3.0.0",
                "@krakenjs/post-robot": "11.0.0",
                "@krakenjs/universal-serialize": "2.0.0",
                "@krakenjs/zalgo-promise": "2.0.1",
                "@krakenjs/zoid": "10.3.3",
                "@paypal/applepay-components": "1.6.0",
                "@paypal/card-components": "1.0.55",
                "@paypal/checkout-components": "5.0.289",
                "@paypal/common-components": "1.0.42",
                "@paypal/connect-loader-component": "1.1.1",
                "@paypal/example-components": "1.0.28",
                "@paypal/funding-components": "1.0.32",
                "@paypal/googlepay-components": "1.2.3",
                "@paypal/identity-components": "5.0.14",
                "@paypal/legal-components": "1.2.2",
                "@paypal/messaging-components": "1.51.0",
                "@paypal/muse-components": "1.3.93",
                "@paypal/sdk-client": "4.0.178",
                "@paypal/sdk-constants": "1.0.134",
                "@paypal/sdk-logos": "2.2.7",
                "bowser": "2.11.0",
                "braintree-web": "3.33.0",
                "card-validator": "4.3.0",
                "core-js-pure": "3.31.1",
                "credit-card-type": "6.3.0",
                "envify": "4.1.0",
                "esprima": "4.0.1",
                "framebus": "3.0.1",
                "hi-base32": "0.5.1",
                "inject-stylesheet": "1.0.0",
                "promise-polyfill": "7.0.2",
                "restricted-input": "1.2.7",
                "through": "2.3.8",
                "typescript": "4.9.5",
                "whatwg-fetch": "3.6.19"
            },
            "dist": {
                "tarball": "https://www.paypalobjects.com/js-sdk-release/5.0.413/paypal/sdk-release/tarballs/5.0.413.tgz"
            },
            "repository": {
                "url": "git://github.com/paypal/paypal-sdk-release.git"
            },
            "gitHead": "17b972c1eb6656171f4624efd11b6168c075e595"
        }
    }
}