{
    "name": "cross-domain-utils",
    "dist-tags": {
        "latest": "2.0.38"
    },
    "versions": {
        "2.0.38": {
            "dependencies": {
                "zalgo-promise": "^1.0.11"
            },
            "dist": {
                "tarball": "https://www.paypalobjects.com/js-sdk-release/cross-domain-utils/tarballs/2.0.38.tgz"
            },
            "repository": {
                "url": "git://github.com/krakenjs/cross-domain-utils.git"
            },
            "gitHead": "11093035ff1a485f080be2492032c4b212aaa07f"
        }
    }
}